MANIFEST.in
ReadMe.md
setup.py
flowpython/ReadMe.rst
flowpython/__init__.py
flowpython/__main__.pyc
flowpython/fp.py
flowpython.egg-info/PKG-INFO
flowpython.egg-info/SOURCES.txt
flowpython.egg-info/dependency_links.txt
flowpython.egg-info/top_level.txt
flowpython/flowpy_src/ReadMe.md
flowpython/flowpy_src/__main__.py
flowpython/flowpy_src/setupfile.py
flowpython/flowpy_switcher/__init__.py
flowpython/flowpy_switcher/setupfile.pyc
flowpython/flowpy_switcher/utils.py
flowpython/linux-64bit/python
flowpython/origin_py/ReadMe.md
flowpython/windows-32bit/python.exe
flowpython/windows-32bit/python3.dll
flowpython/windows-32bit/python36.dll
flowpython/windows-32bit/pythonw.exe
flowpython/windows-64bit/python.exe
flowpython/windows-64bit/python3.dll
flowpython/windows-64bit/python36.dll
flowpython/windows-64bit/pythonw.exe
test/test_arrow.py
test/test_branch.py
test/test_patm.py
test/test_where.py