Metadata-Version: 1.1
Name: flowpython
Version: 0.2.1
Summary: Additional Grammar Compatible to CPython
Home-page: https://github.com/thautwarm/flowpython
Author: Thautwarm
Author-email: twshere@outlook.com
License: MIT License
Keywords: gramamr,ast,readability
Platform: windows
Platform: linux
Classifier: Programming Language :: Python :: 3.6
Classifier: Programming Language :: Python :: Implementation :: CPython
